odoo/addons/coupon_promotion_generate_coupon/README.rst
odoo/addons/coupon_promotion_generate_coupon/__init__.py
odoo/addons/coupon_promotion_generate_coupon/__manifest__.py
odoo/addons/coupon_promotion_generate_coupon/i18n/coupon_promotion_generate_coupon.pot
odoo/addons/coupon_promotion_generate_coupon/models/__init__.py
odoo/addons/coupon_promotion_generate_coupon/models/coupon_program.py
odoo/addons/coupon_promotion_generate_coupon/readme/CONTRIBUTORS.rst
odoo/addons/coupon_promotion_generate_coupon/readme/DESCRIPTION.rst
odoo/addons/coupon_promotion_generate_coupon/readme/USAGE.rst
odoo/addons/coupon_promotion_generate_coupon/static/description/icon.png
odoo/addons/coupon_promotion_generate_coupon/static/description/index.html
odoo/addons/coupon_promotion_generate_coupon/tests/__init__.py
odoo/addons/coupon_promotion_generate_coupon/tests/test_coupon_promotion_generate_coupon.py
odoo/addons/coupon_promotion_generate_coupon/views/coupon_program_views.xml
odoo_addon_coupon_promotion_generate_coupon-15.0.1.0.0.3.dist-info/METADATA
odoo_addon_coupon_promotion_generate_coupon-15.0.1.0.0.3.dist-info/WHEEL
odoo_addon_coupon_promotion_generate_coupon-15.0.1.0.0.3.dist-info/top_level.txt
odoo_addon_coupon_promotion_generate_coupon-15.0.1.0.0.3.dist-info/RECORD
